<?xml version="1.0" encoding="utf-8"?>
<!DOCTYPE hibernate-mapping PUBLIC "-//Hibernate/Hibernate Mapping DTD 3.0//EN"
"http://hibernate.sourceforge.net/hibernate-mapping-3.0.dtd">
<!-- 
    Mapping file autogenerated by MyEclipse Persistence Tools
-->
<hibernate-mapping>
    <class name="com.bank.dms.entity.Project" table="DMS_PROJECT">
        <id name="id" type="java.lang.Integer">
            <column name="ID" precision="22" scale="0" />
            <generator class="sequence">
                <param name="sequence">DMS_PROJECT_SEQ</param>
            </generator>
        </id>
        <many-to-one name="employee" column="MANAGER" fetch="select" />
        <property name="name" type="java.lang.String">
            <column name="NAME" />
        </property>
        <property name="startdate" type="java.sql.Timestamp">
            <column name="STARTDATE" length="7" />
        </property>
        <property name="enddate" type="java.sql.Timestamp">
            <column name="ENDDATE" length="7" />
        </property>
        <property name="status" type="java.lang.String">
            <column name="STATUS" length="6" />
        </property>
        <property name="descr" type="java.lang.String">
            <column name="DESCR" />
        </property>
        <set name="projectEmps" lazy="true" inverse="true" table="DMS_PROJECT_EMP">
            <key>
                <column name="PROJECTID" precision="22" scale="0" />
            </key>
            <one-to-many class="com.bank.dms.entity.Employee" />
        </set>
    </class>
</hibernate-mapping>
